[
	{
		"id" : "06880ba7-e129-4dd7-9e2a-f277e9fad33b",
		"business_id" : "151343d9-158a-4984-aba3-a7ae4d9a1ef3",
		"instagram" : null,
		"facebook" : null,
		"linkedin" : null,
		"twitter" : null,
		"youtube" : null,
		"Created_at" : "2024-08-17 09:55:44.407",
		"Updated_at" : "2024-08-17 09:55:44.407"
	},
	{
		"id" : "2939aca3-c4c8-46f8-a08c-d3cc8e66c1ca",
		"business_id" : "394da118-60d7-4797-b2c2-d9c57ebb5903",
		"instagram" : null,
		"facebook" : null,
		"linkedin" : null,
		"twitter" : null,
		"youtube" : null,
		"Created_at" : "2024-08-15 09:07:20.575",
		"Updated_at" : "2024-08-15 09:07:20.575"
	},
	{
		"id" : "6af7ea54-d624-4bb2-a336-fc65609295d0",
		"business_id" : "82a3c3a7-0c0e-4882-b3d9-ae746ba444da",
		"instagram" : null,
		"facebook" : null,
		"linkedin" : null,
		"twitter" : null,
		"youtube" : null,
		"Created_at" : "2024-09-02 08:52:44.310",
		"Updated_at" : "2024-09-02 08:52:44.310"
	},
	{
		"id" : "6dc7da37-7758-4d10-842c-896e3ade4341",
		"business_id" : "393f4baa-9a65-46cf-b20e-d3773bd140c1",
		"instagram" : null,
		"facebook" : null,
		"linkedin" : null,
		"twitter" : null,
		"youtube" : null,
		"Created_at" : "2024-08-22 09:49:01.322",
		"Updated_at" : "2024-08-22 09:49:01.322"
	},
	{
		"id" : "7a33fd11-a1ff-4578-869b-daacb9a03d3e",
		"business_id" : "1e024fea-861f-4be6-9feb-95aabfb95134",
		"instagram" : null,
		"facebook" : null,
		"linkedin" : null,
		"twitter" : null,
		"youtube" : null,
		"Created_at" : "2024-08-18 06:37:41.196",
		"Updated_at" : "2024-08-18 06:37:41.196"
	},
	{
		"id" : "83fceef5-1027-4ae4-8e7d-e4e3af833bac",
		"business_id" : "89e0431c-ba90-4dd9-9664-4d95567aa4fa",
		"instagram" : null,
		"facebook" : null,
		"linkedin" : null,
		"twitter" : null,
		"youtube" : null,
		"Created_at" : "2024-08-16 17:01:05.551",
		"Updated_at" : "2024-08-16 17:01:05.551"
	},
	{
		"id" : "8502ab6e-0bf7-4ffc-88f7-5b3238f29ae2",
		"business_id" : "58f2dc21-ee76-49cc-8c70-9ce11aa49324",
		"instagram" : null,
		"facebook" : null,
		"linkedin" : null,
		"twitter" : null,
		"youtube" : null,
		"Created_at" : "2024-08-11 06:59:45.006",
		"Updated_at" : "2024-08-11 06:59:45.006"
	},
	{
		"id" : "e24629d6-84ac-46d5-acea-b8a977001dc1",
		"business_id" : "0edd09ee-ee81-4cf5-9bef-f2c0e32f5faf",
		"instagram" : null,
		"facebook" : null,
		"linkedin" : null,
		"twitter" : null,
		"youtube" : null,
		"Created_at" : "2024-08-15 06:20:20.466",
		"Updated_at" : "2024-08-15 06:20:20.466"
	},
	{
		"id" : "e40d561f-8a05-484b-9d9e-fa39d23a9cf0",
		"business_id" : "cbb16128-2b47-49d4-a7ec-2976ff4d36f7",
		"instagram" : null,
		"facebook" : null,
		"linkedin" : null,
		"twitter" : null,
		"youtube" : null,
		"Created_at" : "2024-08-15 09:20:48.670",
		"Updated_at" : "2024-08-15 09:20:48.670"
	}
]
